printstruct/__init__.py
printstruct/main.py
printstruct/constants/__init__.py
printstruct/constants/constant.py
printstruct/services/__init__.py
printstruct/services/draw_tree.py
printstruct/services/list_enteries.py
printstruct/services/parser.py
printstruct/services/zip_project.py
printstruct/utilities/__init__.py
printstruct/utilities/gitignore.py
printstruct/utilities/utils.py
printstruct-1.3.1.dist-info/licenses/LICENSE
printstruct-1.3.1.dist-info/METADATA
printstruct-1.3.1.dist-info/WHEEL
printstruct-1.3.1.dist-info/entry_points.txt
printstruct-1.3.1.dist-info/top_level.txt
printstruct-1.3.1.dist-info/RECORD
