Metadata-Version: 2.4
Name: PrintStruct
Version: 1.3.1
Summary: PrintStruct: print project tree structure and optionally zip it
Author: Shahzaib Ahmad
License: MIT
Requires-Python: >=3.8
License-File: LICENSE
Requires-Dist: pathspec>=0.11
Requires-Dist: pyperclip>=1.5
Dynamic: license-file
